lib_ml/__init__.py
lib_ml/process_data.py
remla24_team8_lib_ml-0.1.5.dist-info/METADATA
remla24_team8_lib_ml-0.1.5.dist-info/WHEEL
remla24_team8_lib_ml-0.1.5.dist-info/RECORD
