Metadata-Version: 2.1
Name: remla24-team8-lib-ml
Version: 0.1.5
Summary: Pre-processing logic used for both model-training and model-service.
Author: Tip ten Brink
Author-email: T.M.tenBrink@student.tudelft.nl
Requires-Python: >=3.12,<4.0
Classifier: Programming Language :: Python :: 3
Classifier: Programming Language :: Python :: 3.12
Requires-Dist: gdown (==4.5.1)
Requires-Dist: joblib (>=1.4.2,<2.0.0)
Requires-Dist: pandas (>=2.2.2,<3.0.0)
Requires-Dist: scikit-learn (>=1.4.2,<2.0.0)
Requires-Dist: tensorflow (>=2.16.1,<3.0.0)
